mehdashti_hashing/__init__.py
mehdashti_hashing/core.py
mehdashti_hashing/py.typed
mehdashti_hashing-0.1.0.dist-info/METADATA
mehdashti_hashing-0.1.0.dist-info/WHEEL
mehdashti_hashing-0.1.0.dist-info/RECORD
