Metadata-Version: 2.4
Name: mehdashti-hashing
Version: 0.1.0
Summary: Fast hashing utilities - xxHash128 for business keys and BLAKE3 for data hashing
Project-URL: Homepage, https://github.com/mehdashti/smart-platform
Project-URL: Repository, https://github.com/mehdashti/smart-platform.git
Project-URL: Issues, https://github.com/mehdashti/smart-platform/issues
Author-email: Mahdi Ashti <mahdi@mehdashti.com>
License: MIT
Keywords: blake3,data-integrity,deduplication,hashing,xxhash
Classifier: Development Status :: 4 - Beta
Classifier: Intended Audience :: Developers
Classifier: License :: OSI Approved :: MIT License
Classifier: Programming Language :: Python :: 3
Classifier: Programming Language :: Python :: 3.13
Requires-Python: >=3.13
Requires-Dist: blake3>=0.4.1
Requires-Dist: xxhash>=3.5.0
Provides-Extra: dev
Requires-Dist: pytest>=8.0.0; extra == 'dev'
Requires-Dist: ruff>=0.8.0; extra == 'dev'
